ramkit/__init__.py
ramkit/baseline.py
ramkit/curvefitting.py
ramkit/filters.py
ramkit/functions.py
ramkit/mlregressor.py
ramkit/normalization.py
ramkit/peakseeking.py
ramkit/spectranization.py
ramkit/static/.gitkeep
ramkit-0.2.0.dist-info/LICENSE
ramkit-0.2.0.dist-info/METADATA
ramkit-0.2.0.dist-info/WHEEL
ramkit-0.2.0.dist-info/top_level.txt
ramkit-0.2.0.dist-info/RECORD
